pydollar_vzla/__init__.py
pydollar_vzla/dolar_price.py
pydollar_vzla/config/__init__.py
pydollar_vzla/config/driver_config.py
pydollar_vzla/sources/__init__.py
pydollar_vzla/sources/base.py
pydollar_vzla/sources/bcv.py
pydollar_vzla/sources/dolartoday.py
pydollar_vzla/sources/monitordolar.py
pydollar_vzla/sources/urls.py
pydollar_vzla-0.1.3.dist-info/LICENSE
pydollar_vzla-0.1.3.dist-info/METADATA
pydollar_vzla-0.1.3.dist-info/WHEEL
pydollar_vzla-0.1.3.dist-info/top_level.txt
pydollar_vzla-0.1.3.dist-info/RECORD
