Metadata-Version: 2.1
Name: pydollar_vzla
Version: 0.1.3
Summary: Una librería en Python para obtener el precio del dólar de diferentes fuentes.
Home-page: https://github.com/AntonioVilaV/pydollar_vzla
Author: Antonio Vila
Author-email: Antonio Vila <vila.antoniojose@gmail.com>
License: MIT License
Keywords: dolar,price,vzla,venezuela,divisa
Classifier: Intended Audience :: Developers
Classifier: License :: OSI Approved :: MIT License
Classifier: Operating System :: OS Independent
Classifier: Programming Language :: Python
Classifier: Topic :: Software Development :: Libraries :: Python Modules
Requires-Python: >=3.6
License-File: LICENSE
Requires-Dist: beautifulsoup4 >=4.12.3
Requires-Dist: requests >=2.31.0
Requires-Dist: lxml >=5.1.0
